{"rows": [{"88c0c8": {"count": 2, "lastIndex": 1, "consec": "True"}, "253b47": {"count": 1, "lastIndex": 2, "consec": "True"}, "a5ebff": {"count": 5, "lastIndex": 7, "consec": "True"}}, {"88c0c8": {"count": 2, "lastIndex": 1, "consec": "True"}, "253b47": {"count": 1, "lastIndex": 2, "consec": "True"}, "a5ebff": {"count": 5, "lastIndex": 7, "consec": "True"}}, {"88c0c8": {"count": 1, "lastIndex": 0, "consec": "True"}, "567eae": {"count": 1, "lastIndex": 1, "consec": "True"}, "253b47": {"count": 1, "lastIndex": 2, "consec": "True"}, "a5ebff": {"count": 5, "lastIndex": 7, "consec": "True"}}, {"253b47": {"count": 2, "lastIndex": 1, "consec": "True"}, "a5ebff": {"count": 6, "lastIndex": 7, "consec": "True"}}, {"c7e2e8": {"count": 1, "lastIndex": 0, "consec": "True"}, "253b47": {"count": 1, "lastIndex": 1, "consec": "True"}, "a5ebff": {"count": 6, "lastIndex": 7, "consec": "True"}}, {"253b47": {"count": 1, "lastIndex": 0, "consec": "True"}, "a5ebff": {"count": 7, "lastIndex": 7, "consec": "True"}}, {"a5ebff": {"count": 8, "lastIndex": 7, "consec": "True"}}, {"a5ebff": {"count": 8, "lastIndex": 7, "consec": "True"}}, {"a5ebff": {"count": 8, "lastIndex": 7, "consec": "True"}}, {"a5ebff": {"count": 8, "lastIndex": 7, "consec": "True"}}, {"a5ebff": {"count": 8, "lastIndex": 7, "consec": "True"}}, {"a5ebff": {"count": 8, "lastIndex": 7, "consec": "True"}}, {"a5ebff": {"count": 8, "lastIndex": 7, "consec": "True"}}, {"a5ebff": {"count": 8, "lastIndex": 7, "consec": "True"}}, {"a5ebff": {"count": 8, "lastIndex": 7, "consec": "True"}}, {"a5ebff": {"count": 8, "lastIndex": 7, "consec": "True"}}], "cols": [{"88c0c8": {"count": 3, "lastIndex": 2, "consec": "True"}, "253b47": {"count": 2, "lastIndex": 5, "consec": "False"}, "c7e2e8": {"count": 1, "lastIndex": 4, "consec": "True"}, "a5ebff": {"count": 10, "lastIndex": 15, "consec": "True"}}, {"88c0c8": {"count": 2, "lastIndex": 1, "consec": "True"}, "567eae": {"count": 1, "lastIndex": 2, "consec": "True"}, "253b47": {"count": 2, "lastIndex": 4, "consec": "True"}, "a5ebff": {"count": 11, "lastIndex": 15, "consec": "True"}}, {"253b47": {"count": 3, "lastIndex": 2, "consec": "True"}, "a5ebff": {"count": 13, "lastIndex": 15, "consec": "True"}}, {"a5ebff": {"count": 16, "lastIndex": 15, "consec": "True"}}, {"a5ebff": {"count": 16, "lastIndex": 15, "consec": "True"}}, {"a5ebff": {"count": 16, "lastIndex": 15, "consec": "True"}}, {"a5ebff": {"count": 16, "lastIndex": 15, "consec": "True"}}, {"a5ebff": {"count": 16, "lastIndex": 15, "consec": "True"}}], "uniqColors": ["88c0c8", "253b47", "c7e2e8", "a5ebff", "567eae"]}