{"rows": [{"445154": {"count": 8, "lastIndex": 7, "consec": "True"}}, {"445154": {"count": 5, "lastIndex": 7, "consec": "False"}, "a5ebff": {"count": 3, "lastIndex": 3, "consec": "True"}}, {"445154": {"count": 5, "lastIndex": 7, "consec": "False"}, "a5ebff": {"count": 3, "lastIndex": 3, "consec": "True"}}, {"445154": {"count": 5, "lastIndex": 7, "consec": "False"}, "a5ebff": {"count": 3, "lastIndex": 4, "consec": "True"}}, {"445154": {"count": 4, "lastIndex": 7, "consec": "False"}, "a5ebff": {"count": 4, "lastIndex": 5, "consec": "True"}}, {"445154": {"count": 1, "lastIndex": 0, "consec": "True"}, "a5ebff": {"count": 7, "lastIndex": 7, "consec": "True"}}, {"a5ebff": {"count": 8, "lastIndex": 7, "consec": "True"}}, {"a5ebff": {"count": 8, "lastIndex": 7, "consec": "True"}}, {"a5ebff": {"count": 8, "lastIndex": 7, "consec": "True"}}, {"a5ebff": {"count": 8, "lastIndex": 7, "consec": "True"}}, {"a5ebff": {"count": 8, "lastIndex": 7, "consec": "True"}}, {"a5ebff": {"count": 8, "lastIndex": 7, "consec": "True"}}, {"a5ebff": {"count": 8, "lastIndex": 7, "consec": "True"}}, {"a5ebff": {"count": 8, "lastIndex": 7, "consec": "True"}}, {"a5ebff": {"count": 8, "lastIndex": 7, "consec": "True"}}, {"a5ebff": {"count": 8, "lastIndex": 7, "consec": "True"}}], "cols": [{"445154": {"count": 6, "lastIndex": 5, "consec": "True"}, "a5ebff": {"count": 10, "lastIndex": 15, "consec": "True"}}, {"445154": {"count": 3, "lastIndex": 4, "consec": "False"}, "a5ebff": {"count": 13, "lastIndex": 15, "consec": "False"}}, {"445154": {"count": 1, "lastIndex": 0, "consec": "True"}, "a5ebff": {"count": 15, "lastIndex": 15, "consec": "True"}}, {"445154": {"count": 1, "lastIndex": 0, "consec": "True"}, "a5ebff": {"count": 15, "lastIndex": 15, "consec": "True"}}, {"445154": {"count": 3, "lastIndex": 2, "consec": "True"}, "a5ebff": {"count": 13, "lastIndex": 15, "consec": "True"}}, {"445154": {"count": 4, "lastIndex": 3, "consec": "True"}, "a5ebff": {"count": 12, "lastIndex": 15, "consec": "True"}}, {"445154": {"count": 5, "lastIndex": 4, "consec": "True"}, "a5ebff": {"count": 11, "lastIndex": 15, "consec": "True"}}, {"445154": {"count": 5, "lastIndex": 4, "consec": "True"}, "a5ebff": {"count": 11, "lastIndex": 15, "consec": "True"}}], "uniqColors": ["445154", "a5ebff"]}