{"rows": [{"e0c822": {"count": 8, "lastIndex": 7, "consec": "True"}}, {"e0c822": {"count": 8, "lastIndex": 7, "consec": "True"}}, {"e0c822": {"count": 8, "lastIndex": 7, "consec": "True"}}, {"e0c822": {"count": 6, "lastIndex": 5, "consec": "True"}, "583e0f": {"count": 2, "lastIndex": 7, "consec": "True"}}, {"e0c822": {"count": 4, "lastIndex": 3, "consec": "True"}, "583e0f": {"count": 2, "lastIndex": 5, "consec": "True"}, "d5d5d5": {"count": 2, "lastIndex": 7, "consec": "True"}}, {"e0c822": {"count": 3, "lastIndex": 2, "consec": "True"}, "583e0f": {"count": 3, "lastIndex": 7, "consec": "False"}, "d5d5d5": {"count": 2, "lastIndex": 6, "consec": "False"}}, {"e0c822": {"count": 5, "lastIndex": 7, "consec": "False"}, "583e0f": {"count": 3, "lastIndex": 5, "consec": "True"}}, {"e0c822": {"count": 7, "lastIndex": 7, "consec": "False"}, "583e0f": {"count": 1, "lastIndex": 3, "consec": "True"}}, {"e0c822": {"count": 6, "lastIndex": 6, "consec": "False"}, "583e0f": {"count": 2, "lastIndex": 7, "consec": "False"}}, {"e0c822": {"count": 5, "lastIndex": 5, "consec": "False"}, "583e0f": {"count": 3, "lastIndex": 7, "consec": "False"}}, {"e0c822": {"count": 4, "lastIndex": 4, "consec": "False"}, "583e0f": {"count": 4, "lastIndex": 7, "consec": "False"}}, {"e0c822": {"count": 7, "lastIndex": 7, "consec": "False"}, "583e0f": {"count": 1, "lastIndex": 2, "consec": "True"}}, {"e0c822": {"count": 4, "lastIndex": 3, "consec": "True"}, "583e0f": {"count": 4, "lastIndex": 7, "consec": "True"}}, {"e0c822": {"count": 6, "lastIndex": 7, "consec": "False"}, "583e0f": {"count": 2, "lastIndex": 4, "consec": "False"}}, {"583e0f": {"count": 2, "lastIndex": 4, "consec": "False"}, "e0c822": {"count": 6, "lastIndex": 7, "consec": "False"}}, {"583e0f": {"count": 5, "lastIndex": 7, "consec": "False"}, "e0c822": {"count": 3, "lastIndex": 6, "consec": "True"}}], "cols": [{"e0c822": {"count": 14, "lastIndex": 13, "consec": "True"}, "583e0f": {"count": 2, "lastIndex": 15, "consec": "True"}}, {"e0c822": {"count": 15, "lastIndex": 14, "consec": "True"}, "583e0f": {"count": 1, "lastIndex": 15, "consec": "True"}}, {"e0c822": {"count": 10, "lastIndex": 14, "consec": "False"}, "583e0f": {"count": 6, "lastIndex": 15, "consec": "False"}}, {"e0c822": {"count": 12, "lastIndex": 14, "consec": "False"}, "583e0f": {"count": 4, "lastIndex": 15, "consec": "False"}}, {"e0c822": {"count": 10, "lastIndex": 15, "consec": "False"}, "583e0f": {"count": 5, "lastIndex": 14, "consec": "False"}, "d5d5d5": {"count": 1, "lastIndex": 5, "consec": "True"}}, {"e0c822": {"count": 11, "lastIndex": 15, "consec": "False"}, "583e0f": {"count": 5, "lastIndex": 12, "consec": "False"}}, {"e0c822": {"count": 10, "lastIndex": 15, "consec": "False"}, "583e0f": {"count": 4, "lastIndex": 12, "consec": "False"}, "d5d5d5": {"count": 2, "lastIndex": 5, "consec": "True"}}, {"e0c822": {"count": 8, "lastIndex": 14, "consec": "False"}, "583e0f": {"count": 7, "lastIndex": 15, "consec": "False"}, "d5d5d5": {"count": 1, "lastIndex": 4, "consec": "True"}}], "uniqColors": ["e0c822", "583e0f", "d5d5d5"]}