{"rows": [{"6c4c3b": {"count": 4, "lastIndex": 3, "consec": "True"}, "5ea6d6": {"count": 4, "lastIndex": 7, "consec": "True"}}, {"6c4c3b": {"count": 3, "lastIndex": 2, "consec": "True"}, "5ea6d6": {"count": 5, "lastIndex": 7, "consec": "True"}}, {"6c4c3b": {"count": 3, "lastIndex": 2, "consec": "True"}, "5ea6d6": {"count": 5, "lastIndex": 7, "consec": "True"}}, {"6c4c3b": {"count": 2, "lastIndex": 1, "consec": "True"}, "5ea6d6": {"count": 6, "lastIndex": 7, "consec": "True"}}, {"6c4c3b": {"count": 1, "lastIndex": 0, "consec": "True"}, "5ea6d6": {"count": 7, "lastIndex": 7, "consec": "True"}}, {"5ea6d6": {"count": 8, "lastIndex": 7, "consec": "True"}}, {"5ea6d6": {"count": 8, "lastIndex": 7, "consec": "True"}}, {"5ea6d6": {"count": 7, "lastIndex": 6, "consec": "True"}, "6c4c3b": {"count": 1, "lastIndex": 7, "consec": "True"}}, {"5ea6d6": {"count": 6, "lastIndex": 5, "consec": "True"}, "6c4c3b": {"count": 1, "lastIndex": 6, "consec": "True"}, "a5ebff": {"count": 1, "lastIndex": 7, "consec": "True"}}, {"5ea6d6": {"count": 6, "lastIndex": 5, "consec": "True"}, "6c4c3b": {"count": 1, "lastIndex": 6, "consec": "True"}, "a5ebff": {"count": 1, "lastIndex": 7, "consec": "True"}}, {"5ea6d6": {"count": 5, "lastIndex": 4, "consec": "True"}, "6c4c3b": {"count": 1, "lastIndex": 5, "consec": "True"}, "a5ebff": {"count": 2, "lastIndex": 7, "consec": "True"}}, {"5ea6d6": {"count": 4, "lastIndex": 3, "consec": "True"}, "6c4c3b": {"count": 1, "lastIndex": 4, "consec": "True"}, "a5ebff": {"count": 3, "lastIndex": 7, "consec": "True"}}, {"6c4c3b": {"count": 4, "lastIndex": 3, "consec": "True"}, "a5ebff": {"count": 4, "lastIndex": 7, "consec": "True"}}, {"6c4c3b": {"count": 1, "lastIndex": 0, "consec": "True"}, "a5ebff": {"count": 7, "lastIndex": 7, "consec": "True"}}, {"6c4c3b": {"count": 1, "lastIndex": 0, "consec": "True"}, "a5ebff": {"count": 7, "lastIndex": 7, "consec": "True"}}, {"6c4c3b": {"count": 1, "lastIndex": 0, "consec": "True"}, "a5ebff": {"count": 7, "lastIndex": 7, "consec": "True"}}], "cols": [{"6c4c3b": {"count": 9, "lastIndex": 15, "consec": "False"}, "5ea6d6": {"count": 7, "lastIndex": 11, "consec": "True"}}, {"6c4c3b": {"count": 5, "lastIndex": 12, "consec": "False"}, "5ea6d6": {"count": 8, "lastIndex": 11, "consec": "True"}, "a5ebff": {"count": 3, "lastIndex": 15, "consec": "True"}}, {"6c4c3b": {"count": 4, "lastIndex": 12, "consec": "False"}, "5ea6d6": {"count": 9, "lastIndex": 11, "consec": "True"}, "a5ebff": {"count": 3, "lastIndex": 15, "consec": "True"}}, {"6c4c3b": {"count": 2, "lastIndex": 12, "consec": "False"}, "5ea6d6": {"count": 11, "lastIndex": 11, "consec": "True"}, "a5ebff": {"count": 3, "lastIndex": 15, "consec": "True"}}, {"5ea6d6": {"count": 11, "lastIndex": 10, "consec": "True"}, "6c4c3b": {"count": 1, "lastIndex": 11, "consec": "True"}, "a5ebff": {"count": 4, "lastIndex": 15, "consec": "True"}}, {"5ea6d6": {"count": 10, "lastIndex": 9, "consec": "True"}, "6c4c3b": {"count": 1, "lastIndex": 10, "consec": "True"}, "a5ebff": {"count": 5, "lastIndex": 15, "consec": "True"}}, {"5ea6d6": {"count": 8, "lastIndex": 7, "consec": "True"}, "6c4c3b": {"count": 2, "lastIndex": 9, "consec": "True"}, "a5ebff": {"count": 6, "lastIndex": 15, "consec": "True"}}, {"5ea6d6": {"count": 7, "lastIndex": 6, "consec": "True"}, "6c4c3b": {"count": 1, "lastIndex": 7, "consec": "True"}, "a5ebff": {"count": 8, "lastIndex": 15, "consec": "True"}}], "uniqColors": ["6c4c3b", "5ea6d6", "a5ebff"]}