{"rows": [{"f8a04c": {"count": 6, "lastIndex": 5, "consec": "True"}, "bd4b15": {"count": 2, "lastIndex": 7, "consec": "True"}}, {"f8a04c": {"count": 3, "lastIndex": 4, "consec": "False"}, "bd4b15": {"count": 5, "lastIndex": 7, "consec": "False"}}, {"bd4b15": {"count": 6, "lastIndex": 7, "consec": "False"}, "f8a04c": {"count": 2, "lastIndex": 3, "consec": "False"}}, {"bd4b15": {"count": 8, "lastIndex": 7, "consec": "True"}}, {"bd4b15": {"count": 7, "lastIndex": 6, "consec": "True"}, "184054": {"count": 1, "lastIndex": 7, "consec": "True"}}, {"bd4b15": {"count": 7, "lastIndex": 6, "consec": "True"}, "184054": {"count": 1, "lastIndex": 7, "consec": "True"}}, {"f8a04c": {"count": 7, "lastIndex": 6, "consec": "True"}, "bd4b15": {"count": 1, "lastIndex": 7, "consec": "True"}}, {"bd4b15": {"count": 1, "lastIndex": 0, "consec": "True"}, "184054": {"count": 2, "lastIndex": 2, "consec": "True"}, "f8a04c": {"count": 5, "lastIndex": 7, "consec": "True"}}, {"a5ebff": {"count": 3, "lastIndex": 2, "consec": "True"}, "bd4b15": {"count": 1, "lastIndex": 3, "consec": "True"}, "184054": {"count": 4, "lastIndex": 7, "consec": "True"}}, {"a5ebff": {"count": 8, "lastIndex": 7, "consec": "True"}}, {"a5ebff": {"count": 8, "lastIndex": 7, "consec": "True"}}, {"a5ebff": {"count": 8, "lastIndex": 7, "consec": "True"}}, {"a5ebff": {"count": 7, "lastIndex": 6, "consec": "True"}, "bd4b15": {"count": 1, "lastIndex": 7, "consec": "True"}}, {"a5ebff": {"count": 7, "lastIndex": 6, "consec": "True"}, "184054": {"count": 1, "lastIndex": 7, "consec": "True"}}, {"a5ebff": {"count": 8, "lastIndex": 7, "consec": "True"}}, {"a5ebff": {"count": 8, "lastIndex": 7, "consec": "True"}}], "cols": [{"f8a04c": {"count": 3, "lastIndex": 6, "consec": "False"}, "bd4b15": {"count": 5, "lastIndex": 7, "consec": "False"}, "a5ebff": {"count": 8, "lastIndex": 15, "consec": "True"}}, {"f8a04c": {"count": 3, "lastIndex": 6, "consec": "False"}, "bd4b15": {"count": 4, "lastIndex": 5, "consec": "False"}, "184054": {"count": 1, "lastIndex": 7, "consec": "True"}, "a5ebff": {"count": 8, "lastIndex": 15, "consec": "True"}}, {"f8a04c": {"count": 3, "lastIndex": 6, "consec": "False"}, "bd4b15": {"count": 4, "lastIndex": 5, "consec": "True"}, "184054": {"count": 1, "lastIndex": 7, "consec": "True"}, "a5ebff": {"count": 8, "lastIndex": 15, "consec": "True"}}, {"f8a04c": {"count": 4, "lastIndex": 7, "consec": "False"}, "bd4b15": {"count": 5, "lastIndex": 8, "consec": "False"}, "a5ebff": {"count": 7, "lastIndex": 15, "consec": "True"}}, {"f8a04c": {"count": 4, "lastIndex": 7, "consec": "False"}, "bd4b15": {"count": 4, "lastIndex": 5, "consec": "True"}, "184054": {"count": 1, "lastIndex": 8, "consec": "True"}, "a5ebff": {"count": 7, "lastIndex": 15, "consec": "True"}}, {"f8a04c": {"count": 3, "lastIndex": 7, "consec": "False"}, "bd4b15": {"count": 5, "lastIndex": 5, "consec": "True"}, "184054": {"count": 1, "lastIndex": 8, "consec": "True"}, "a5ebff": {"count": 7, "lastIndex": 15, "consec": "True"}}, {"bd4b15": {"count": 6, "lastIndex": 5, "consec": "True"}, "f8a04c": {"count": 2, "lastIndex": 7, "consec": "True"}, "184054": {"count": 1, "lastIndex": 8, "consec": "True"}, "a5ebff": {"count": 7, "lastIndex": 15, "consec": "True"}}, {"bd4b15": {"count": 6, "lastIndex": 12, "consec": "False"}, "184054": {"count": 4, "lastIndex": 13, "consec": "False"}, "f8a04c": {"count": 1, "lastIndex": 7, "consec": "True"}, "a5ebff": {"count": 5, "lastIndex": 15, "consec": "False"}}], "uniqColors": ["f8a04c", "bd4b15", "a5ebff", "184054"]}