{"rows": [{"e3e3e8": {"count": 5, "lastIndex": 4, "consec": "True"}, "3e87b8": {"count": 3, "lastIndex": 7, "consec": "True"}}, {"e3e3e8": {"count": 8, "lastIndex": 7, "consec": "True"}}, {"e3e3e8": {"count": 8, "lastIndex": 7, "consec": "True"}}, {"e3e3e8": {"count": 8, "lastIndex": 7, "consec": "True"}}, {"e3e3e8": {"count": 8, "lastIndex": 7, "consec": "True"}}, {"3e87b8": {"count": 1, "lastIndex": 0, "consec": "True"}, "e3e3e8": {"count": 7, "lastIndex": 7, "consec": "True"}}, {"a5ebff": {"count": 1, "lastIndex": 0, "consec": "True"}, "2c3c50": {"count": 1, "lastIndex": 1, "consec": "True"}, "3e87b8": {"count": 1, "lastIndex": 2, "consec": "True"}, "e3e3e8": {"count": 5, "lastIndex": 7, "consec": "True"}}, {"a5ebff": {"count": 3, "lastIndex": 2, "consec": "True"}, "2c3c50": {"count": 1, "lastIndex": 3, "consec": "True"}, "3e87b8": {"count": 1, "lastIndex": 4, "consec": "True"}, "e3e3e8": {"count": 3, "lastIndex": 7, "consec": "True"}}, {"a5ebff": {"count": 5, "lastIndex": 4, "consec": "True"}, "2c3c50": {"count": 2, "lastIndex": 6, "consec": "True"}, "3e87b8": {"count": 1, "lastIndex": 7, "consec": "True"}}, {"a5ebff": {"count": 8, "lastIndex": 7, "consec": "True"}}, {"a5ebff": {"count": 8, "lastIndex": 7, "consec": "True"}}, {"a5ebff": {"count": 8, "lastIndex": 7, "consec": "True"}}, {"a5ebff": {"count": 8, "lastIndex": 7, "consec": "True"}}, {"a5ebff": {"count": 8, "lastIndex": 7, "consec": "True"}}, {"a5ebff": {"count": 8, "lastIndex": 7, "consec": "True"}}, {"a5ebff": {"count": 8, "lastIndex": 7, "consec": "True"}}], "cols": [{"e3e3e8": {"count": 5, "lastIndex": 4, "consec": "True"}, "3e87b8": {"count": 1, "lastIndex": 5, "consec": "True"}, "a5ebff": {"count": 10, "lastIndex": 15, "consec": "True"}}, {"e3e3e8": {"count": 6, "lastIndex": 5, "consec": "True"}, "2c3c50": {"count": 1, "lastIndex": 6, "consec": "True"}, "a5ebff": {"count": 9, "lastIndex": 15, "consec": "True"}}, {"e3e3e8": {"count": 6, "lastIndex": 5, "consec": "True"}, "3e87b8": {"count": 1, "lastIndex": 6, "consec": "True"}, "a5ebff": {"count": 9, "lastIndex": 15, "consec": "True"}}, {"e3e3e8": {"count": 7, "lastIndex": 6, "consec": "True"}, "2c3c50": {"count": 1, "lastIndex": 7, "consec": "True"}, "a5ebff": {"count": 8, "lastIndex": 15, "consec": "True"}}, {"e3e3e8": {"count": 7, "lastIndex": 6, "consec": "True"}, "3e87b8": {"count": 1, "lastIndex": 7, "consec": "True"}, "a5ebff": {"count": 8, "lastIndex": 15, "consec": "True"}}, {"3e87b8": {"count": 1, "lastIndex": 0, "consec": "True"}, "e3e3e8": {"count": 7, "lastIndex": 7, "consec": "True"}, "2c3c50": {"count": 1, "lastIndex": 8, "consec": "True"}, "a5ebff": {"count": 7, "lastIndex": 15, "consec": "True"}}, {"3e87b8": {"count": 1, "lastIndex": 0, "consec": "True"}, "e3e3e8": {"count": 7, "lastIndex": 7, "consec": "True"}, "2c3c50": {"count": 1, "lastIndex": 8, "consec": "True"}, "a5ebff": {"count": 7, "lastIndex": 15, "consec": "True"}}, {"3e87b8": {"count": 2, "lastIndex": 8, "consec": "False"}, "e3e3e8": {"count": 7, "lastIndex": 7, "consec": "True"}, "a5ebff": {"count": 7, "lastIndex": 15, "consec": "True"}}], "uniqColors": ["e3e3e8", "3e87b8", "a5ebff", "2c3c50"]}